CHANGES.rst
LICENSE
MANIFEST.in
README.rst
setup.py
django_monitor/__init__.py
django_monitor/actions.py
django_monitor/admin.py
django_monitor/conf.py
django_monitor/filter.py
django_monitor/middleware.py
django_monitor/models.py
django_monitor/util.py
django_monitor.egg-info/PKG-INFO
django_monitor.egg-info/SOURCES.txt
django_monitor.egg-info/dependency_links.txt
django_monitor.egg-info/requires.txt
django_monitor.egg-info/top_level.txt
django_monitor.egg-info/zip-safe
django_monitor/templates/admin/django_monitor/monitorentry/change_list.html
django_monitor/tests/__init__.py
django_monitor/tests/tests.py
django_monitor/tests/urls.py
django_monitor/tests/test_app/__init__.py
django_monitor/tests/test_app/admin.py
django_monitor/tests/test_app/models.py
docs/Makefile
docs/make.bat
docs/source/admin_howto.rst
docs/source/conf.py
docs/source/dev_howto.rst
docs/source/index.rst
docs/source/intro.rst
docs/source/_images/moderation_actions.jpg
docs/source/_images/moderation_changelink.jpg
docs/source/_images/moderation_filter.jpg
docs/source/_images/moderation_queue.jpg
docs/source/_images/moderation_status_column.jpg