Metadata-Version: 1.0
Name: django-monitor
Version: 0.2.1a
Summary: Django app to moderate model objects
Home-page: http://bitbucket.org/rajeesh/django-monitor
Author: Rajeesh Nair
Author-email: rajeeshrnair@gmail.com
License: BSD
Keywords: django moderation models
Platform: UNKNOWN
Classifier: Development Status :: 4 - Beta
Classifier: Environment :: Web Environment
Classifier: Intended Audience :: Developers
Classifier: License :: OSI Approved :: BSD License
Classifier: Operating System :: OS Independent
Classifier: Programming Language :: Python
Classifier: Framework :: Django
